brainlessdb/__init__.py
brainlessdb/bucket.py
brainlessdb/client.py
brainlessdb/collection.py
brainlessdb/fields.py
brainlessdb/struct.py
brainlessdb-0.4.1.dist-info/METADATA
brainlessdb-0.4.1.dist-info/WHEEL
brainlessdb-0.4.1.dist-info/RECORD
