Metadata-Version: 2.4
Name: brainlessdb
Version: 0.4.1
Summary: Typed collections backed by NATS JetStream KV
Author-email: "INSOFT s.r.o." <helpdesk@insoft.cz>
License-Expression: MIT
Requires-Python: >=3.9
Requires-Dist: msgspec>=0.18.0
Requires-Dist: nats-py>=2.10.0
